odoo/addons/crm_partner_creator/__init__.py
odoo/addons/crm_partner_creator/__manifest__.py
odoo/addons/crm_partner_creator/models/__init__.py
odoo/addons/crm_partner_creator/models/crm_lead.py
odoo/addons/crm_partner_creator/models/crm_partner_creator_config.py
odoo/addons/crm_partner_creator/security/ir.model.access.csv
odoo/addons/crm_partner_creator/views/crm_lead.xml
odoo/addons/crm_partner_creator/views/crm_partner_creator_config.xml
odoo12_addon_crm_partner_creator-12.0.0.0.2.dist-info/METADATA
odoo12_addon_crm_partner_creator-12.0.0.0.2.dist-info/WHEEL
odoo12_addon_crm_partner_creator-12.0.0.0.2.dist-info/top_level.txt
odoo12_addon_crm_partner_creator-12.0.0.0.2.dist-info/RECORD
